culligan/__init__.py
culligan/const.py
culligan/culliganiot_device.py
culligan/exc.py
culligan/uniapi_culliganiot.py
culligan-1.1.5.dist-info/LICENSE
culligan-1.1.5.dist-info/METADATA
culligan-1.1.5.dist-info/WHEEL
culligan-1.1.5.dist-info/top_level.txt
culligan-1.1.5.dist-info/RECORD
