Metadata-Version: 2.2
Name: culligan
Version: 1.1.5
Summary: Python API for Culligan products
Home-page: https://github.com/rewardone/culligan
Author: Reward One
Author-email: Reward One <rewardone@gmail.com>
Project-URL: Homepage, https://github.com/rewardone/culligan
Project-URL: Bug Tracker, https://github.com/rewardone/culligan/issues
Classifier: Programming Language :: Python :: 3
Classifier: License :: OSI Approved :: MIT License
Classifier: Operating System :: OS Independent
Requires-Python: >=3.10
License-File: LICENSE
Requires-Dist: aiohttp>=3.8.4
Requires-Dist: requests>=2.31.0
Requires-Dist: ujson>=5.8.0
Requires-Dist: ayla_iot_unofficial>=1.4.6
Dynamic: author
Dynamic: home-page
